{
  "indexes": [
    {
      "collectionGroup": "attendance",
      "queryScope": "COLLECTION",
      "fields": [
        {
          "fieldPath": "studentId",
          "order": "ASCENDING"
        },
        {
          "fieldPath": "markedAt",
          "order": "DESCENDING"
        }
      ]
    },
    {
      "collectionGroup": "attendance",
      "queryScope": "COLLECTION",
      "fields": [
        {
          "fieldPath": "studentId",
          "order": "ASCENDING"
        },
        {
          "fieldPath": "subjectId",
          "order": "ASCENDING"
        },
        {
          "fieldPath": "markedAt",
          "order": "DESCENDING"
        }
      ]
    },
    {
      "collectionGroup": "attendance",
      "queryScope": "COLLECTION",
      "fields": [
        {
          "fieldPath": "sessionId",
          "order": "ASCENDING"
        },
        {
          "fieldPath": "studentId",
          "order": "ASCENDING"
        }
      ]
    },
    {
      "collectionGroup": "sessions",
      "queryScope": "COLLECTION",
      "fields": [
        {
          "fieldPath": "subjectId",
          "order": "ASCENDING"
        },
        {
          "fieldPath": "date",
          "order": "ASCENDING"
        },
        {
          "fieldPath": "createdAt",
          "order": "DESCENDING"
        }
      ]
    },
    {
      "collectionGroup": "sessions",
      "queryScope": "COLLECTION",
      "fields": [
        {
          "fieldPath": "batchId",
          "order": "ASCENDING"
        },
        {
          "fieldPath": "subjectName",
          "order": "ASCENDING"
        },
        {
          "fieldPath": "createdAt",
          "order": "DESCENDING"
        }
      ]
    },
    {
      "collectionGroup": "sessions",
      "queryScope": "COLLECTION",
      "fields": [
        {
          "fieldPath": "batchId",
          "order": "ASCENDING"
        },
        {
          "fieldPath": "date",
          "order": "ASCENDING"
        },
        {
          "fieldPath": "createdAt",
          "order": "DESCENDING"
        }
      ]
    },
    {
      "collectionGroup": "sessions",
      "queryScope": "COLLECTION",
      "fields": [
        {
          "fieldPath": "batchId",
          "order": "ASCENDING"
        },
        {
          "fieldPath": "createdAt",
          "order": "DESCENDING"
        }
      ]
    },
    {
      "collectionGroup": "sessions",
      "queryScope": "COLLECTION",
      "fields": [
        {
          "fieldPath": "status",
          "order": "ASCENDING"
        },
        {
          "fieldPath": "createdAt",
          "order": "DESCENDING"
        }
      ]
    },
    {
      "collectionGroup": "attendance_summary",
      "queryScope": "COLLECTION",
      "fields": [
        {
          "fieldPath": "attendancePercentage",
          "order": "ASCENDING"
        },
        {
          "fieldPath": "batchId",
          "order": "ASCENDING"
        }
      ]
    },
    {
      "collectionGroup": "attendance_summary",
      "queryScope": "COLLECTION",
      "fields": [
        {
          "fieldPath": "attendancePercentage",
          "order": "ASCENDING"
        },
        {
          "fieldPath": "subjectId",
          "order": "ASCENDING"
        }
      ]
    }
  ],
  "fieldOverrides": []
}
